odoo_filter_addons/__init__.py
odoo_filter_addons/main.py
odoo_filter_addons/version.py
odoo_filter_addons-1.3.3.dist-info/METADATA
odoo_filter_addons-1.3.3.dist-info/WHEEL
odoo_filter_addons-1.3.3.dist-info/entry_points.txt
odoo_filter_addons-1.3.3.dist-info/top_level.txt
odoo_filter_addons-1.3.3.dist-info/RECORD
