Metadata-Version: 2.1
Name: odoo_filter_addons
Version: 1.3.3
Summary: Simple utlity to filter odoo addons into a single directory
Author-email: Pablo Esteban <pablo.esteban@forgeflow.com>
Classifier: Intended Audience :: Developers
Classifier: Topic :: Utilities
Classifier: Operating System :: POSIX
Classifier: Framework :: Odoo
Classifier: Programming Language :: Python :: 3
Requires-Python: >=3
Requires-Dist: pyyaml
Requires-Dist: click
Requires-Dist: python-dotenv
Requires-Dist: plumbum
Requires-Dist: git-aggregator >=3.0.0
